planetarypy/__init__.py
planetarypy/_modidx.py
planetarypy/_nbdev.py
planetarypy/ard.py
planetarypy/ciss.py
planetarypy/config.py
planetarypy/ctx.py
planetarypy/db.py
planetarypy/diviner.py
planetarypy/exceptions.py
planetarypy/geotools.py
planetarypy/hirise.py
planetarypy/utils.py
planetarypy/uvis.py
planetarypy/data/__init__.py
planetarypy/data/planetarypy_config.toml
planetarypy/pds/__init__.py
planetarypy/pds/apps.py
planetarypy/pds/crism_index.py
planetarypy/pds/ctx_index.py
planetarypy/pds/indexes.py
planetarypy/pds/lroc_index.py
planetarypy/pds/opusapi.py
planetarypy/pds/utils.py
planetarypy/spice/__init__.py
planetarypy/spice/kernels.py
planetarypy/spice/spicer.py
planetarypy-0.32.1.dist-info/LICENSE
planetarypy-0.32.1.dist-info/METADATA
planetarypy-0.32.1.dist-info/WHEEL
planetarypy-0.32.1.dist-info/entry_points.txt
planetarypy-0.32.1.dist-info/top_level.txt
planetarypy-0.32.1.dist-info/RECORD
