Metadata-Version: 2.1
Name: planetarypy
Version: 0.32.1
Summary: Python Tools for Planetary Science
Home-page: https://github.com/michaelaye/nbplanetary
Author: Michael Aye
Author-email: kmichael.aye@gmail.com
License: MIT License
Keywords: planetary science,data analysis
Classifier: Development Status :: 4 - Beta
Classifier: Intended Audience :: Developers
Classifier: Natural Language :: English
Classifier: Programming Language :: Python :: 3.9
Classifier: Programming Language :: Python :: 3.10
Classifier: License :: OSI Approved :: MIT License
Requires-Python: >=3.9
License-File: LICENSE
Requires-Dist: tomlkit
Requires-Dist: pandas
Requires-Dist: pvl
Requires-Dist: numpy
Requires-Dist: python-dateutil
Requires-Dist: tqdm
Requires-Dist: lxml
Requires-Dist: yarl
Requires-Dist: kalasiris
Requires-Dist: dask
Requires-Dist: fastparquet
Requires-Dist: rioxarray
Requires-Dist: matplotlib
Requires-Dist: hvplot
Requires-Dist: requests
Requires-Dist: astropy
Requires-Dist: fastcore
Requires-Dist: datashader
Requires-Dist: ipywidgets
Requires-Dist: gdal
Requires-Dist: spiceypy
Requires-Dist: rasterio
Provides-Extra: dev
